<?xml version="1.0" encoding="UTF-8"?>
<con:testCase id="3af16f1a-aa1d-4276-98e8-d0510fc74544" discardOkResults="true" failOnError="true" failTestCaseOnErrors="true" keepSession="false" name="SecondTestCase" searchProperties="true" timeout="0" xmlns:con="http://eviware.com/soapui/config"><con:settings><con:setting id="3af16f1a-aa1d-4276-98e8-d0510fc74544fileName">SecondTestCase</con:setting></con:settings><con:savedRecentRuns>1</con:savedRecentRuns><con:testStep type="restrequest" name="REST Request" id="b7b05202-c99b-4e91-a039-904912dcf04b"><con:settings/><con:config service="http://maps.googleapis.com" resourcePath="/maps/api/geocode/{format}" methodName="Xml" xsi:type="con:RestRequestStep" xmlns:xsi="http://www.w3.org/2001/XMLSchema-instance"><con:restRequest name="REST Request" id="feb8576e-f5bb-4c5e-8961-fd500fa2d0fc" mediaType="application/json"><con:settings><con:setting id="com.eviware.soapui.impl.wsdl.WsdlRequest@request-headers">&lt;xml-fragment/></con:setting></con:settings><con:endpoint>http://maps.googleapis.com</con:endpoint><con:request/><con:originalUri>http://maps.googleapis.com/maps/api/geocode/xml</con:originalUri><con:assertion type="Response SLA Assertion" id="c8ae6110-afc8-41a5-8cbb-5175c72aae39" name="Response SLA"><con:configuration><SLA>1000</SLA></con:configuration></con:assertion><con:assertion type="JsonPath Existence Match" id="9b70798e-c8ac-4a99-b270-f7bcff5bbe43" name="Check for existence of [formatted_address]"><con:configuration><path>$['results'][0]['formatted_address']</path><content>true</content><allowWildcards>false</allowWildcards><ignoreNamspaceDifferences>false</ignoreNamspaceDifferences><ignoreComments>false</ignoreComments></con:configuration></con:assertion><con:credentials><con:selectedAuthProfile>Inherit From Parent</con:selectedAuthProfile><con:authType>No Authorization</con:authType></con:credentials><con:jmsConfig JMSDeliveryMode="PERSISTENT"/><con:parameters>
  <con:entry key="address" value="Austin"/>
  <con:entry key="format" value="json"/>
</con:parameters><con:parameterOrder><con:entry>address</con:entry><con:entry>language</con:entry><con:entry>format</con:entry></con:parameterOrder></con:restRequest></con:config></con:testStep><con:testStep type="restrequest" name="REST Request 2" id="64de45d8-2f38-4481-88fb-b34772af57dc"><con:settings/><con:config service="http://maps.googleapis.com" methodName="Xml" resourcePath="/maps/api/geocode/{format}" xsi:type="con:RestRequestStep" xmlns:xsi="http://www.w3.org/2001/XMLSchema-instance"><con:restRequest name="REST Request" id="571a8ffc-efc1-4834-9044-35fd334f107b" mediaType="application/json"><con:settings><con:setting id="com.eviware.soapui.impl.wsdl.WsdlRequest@request-headers">&lt;xml-fragment/></con:setting></con:settings><con:encoding>UTF-8</con:encoding><con:endpoint>http://maps.googleapis.com</con:endpoint><con:request/><con:originalUri>http://maps.googleapis.com/maps/api/geocode/</con:originalUri><con:credentials><con:selectedAuthProfile>Inherit From Parent</con:selectedAuthProfile><con:authType>No Authorization</con:authType></con:credentials><con:jmsConfig JMSDeliveryMode="PERSISTENT"/><con:parameters>
  <con:entry key="address" value="${REST Request#Response#$['results'][0]['address_components'][0]['long_name']}"/>
  <con:entry key="format" value="json"/>
</con:parameters></con:restRequest></con:config></con:testStep><con:properties/><con:reportParameters/><con:breakPoints><con:testStepId>64de45d8-2f38-4481-88fb-b34772af57dc</con:testStepId><con:status>NONE</con:status><con:properties/></con:breakPoints></con:testCase>